[
  {
    "operation": {
      "classname": "com.google.common.collect.ImmutableSortedMultisetFauxverideShim",
      "name": "builder",
      "parameterTypes": []
    },
    "identifiers": {
      "parameters": [],
      "receiverName": "receiverObjectID",
      "returnName": "methodResultID"
    },
    "throws": [
      {
        "exception": "java.lang.UnsupportedOperationException",
        "description": "@throws java.lang.UnsupportedOperationException always.",
        "guard": {
          "condition": "true",
          "description": "always."
        }
      }
    ],
    "post": [],
    "pre": []
  },
  {
    "operation": {
      "classname": "com.google.common.collect.ImmutableSortedMultisetFauxverideShim",
      "name": "of",
      "parameterTypes": [
        "java.lang.Object"
      ]
    },
    "identifiers": {
      "parameters": [
        "element"
      ],
      "receiverName": "receiverObjectID",
      "returnName": "methodResultID"
    },
    "throws": [
      {
        "exception": "java.lang.UnsupportedOperationException",
        "description": "@throws java.lang.UnsupportedOperationException always.",
        "guard": {
          "condition": "true",
          "description": "always."
        }
      }
    ],
    "post": [],
    "pre": []
  },
  {
    "operation": {
      "classname": "com.google.common.collect.ImmutableSortedMultisetFauxverideShim",
      "name": "of",
      "parameterTypes": [
        "java.lang.Object",
        "java.lang.Object"
      ]
    },
    "identifiers": {
      "parameters": [
        "e1",
        "e2"
      ],
      "receiverName": "receiverObjectID",
      "returnName": "methodResultID"
    },
    "throws": [
      {
        "exception": "java.lang.UnsupportedOperationException",
        "description": "@throws java.lang.UnsupportedOperationException always.",
        "guard": {
          "condition": "true",
          "description": "always."
        }
      }
    ],
    "post": [],
    "pre": []
  },
  {
    "operation": {
      "classname": "com.google.common.collect.ImmutableSortedMultisetFauxverideShim",
      "name": "of",
      "parameterTypes": [
        "java.lang.Object",
        "java.lang.Object",
        "java.lang.Object"
      ]
    },
    "identifiers": {
      "parameters": [
        "e1",
        "e2",
        "e3"
      ],
      "receiverName": "receiverObjectID",
      "returnName": "methodResultID"
    },
    "throws": [
      {
        "exception": "java.lang.UnsupportedOperationException",
        "description": "@throws java.lang.UnsupportedOperationException always.",
        "guard": {
          "condition": "true",
          "description": "always."
        }
      }
    ],
    "post": [],
    "pre": []
  },
  {
    "operation": {
      "classname": "com.google.common.collect.ImmutableSortedMultisetFauxverideShim",
      "name": "of",
      "parameterTypes": [
        "java.lang.Object",
        "java.lang.Object",
        "java.lang.Object",
        "java.lang.Object"
      ]
    },
    "identifiers": {
      "parameters": [
        "e1",
        "e2",
        "e3",
        "e4"
      ],
      "receiverName": "receiverObjectID",
      "returnName": "methodResultID"
    },
    "throws": [
      {
        "exception": "java.lang.UnsupportedOperationException",
        "description": "@throws java.lang.UnsupportedOperationException always.",
        "guard": {
          "condition": "true",
          "description": "always."
        }
      }
    ],
    "post": [],
    "pre": []
  },
  {
    "operation": {
      "classname": "com.google.common.collect.ImmutableSortedMultisetFauxverideShim",
      "name": "of",
      "parameterTypes": [
        "java.lang.Object",
        "java.lang.Object",
        "java.lang.Object",
        "java.lang.Object",
        "java.lang.Object"
      ]
    },
    "identifiers": {
      "parameters": [
        "e1",
        "e2",
        "e3",
        "e4",
        "e5"
      ],
      "receiverName": "receiverObjectID",
      "returnName": "methodResultID"
    },
    "throws": [
      {
        "exception": "java.lang.UnsupportedOperationException",
        "description": "@throws java.lang.UnsupportedOperationException always.",
        "guard": {
          "condition": "true",
          "description": "always."
        }
      }
    ],
    "post": [],
    "pre": []
  },
  {
    "operation": {
      "classname": "com.google.common.collect.ImmutableSortedMultisetFauxverideShim",
      "name": "of",
      "parameterTypes": [
        "java.lang.Object",
        "java.lang.Object",
        "java.lang.Object",
        "java.lang.Object",
        "java.lang.Object",
        "java.lang.Object",
        "[Ljava.lang.Object;"
      ]
    },
    "identifiers": {
      "parameters": [
        "e1",
        "e2",
        "e3",
        "e4",
        "e5",
        "e6",
        "remaining"
      ],
      "receiverName": "receiverObjectID",
      "returnName": "methodResultID"
    },
    "throws": [
      {
        "exception": "java.lang.UnsupportedOperationException",
        "description": "@throws java.lang.UnsupportedOperationException always.",
        "guard": {
          "condition": "true",
          "description": "always."
        }
      }
    ],
    "post": [],
    "pre": []
  },
  {
    "operation": {
      "classname": "com.google.common.collect.ImmutableSortedMultisetFauxverideShim",
      "name": "copyOf",
      "parameterTypes": [
        "[Ljava.lang.Object;"
      ]
    },
    "identifiers": {
      "parameters": [
        "elements"
      ],
      "receiverName": "receiverObjectID",
      "returnName": "methodResultID"
    },
    "throws": [
      {
        "exception": "java.lang.UnsupportedOperationException",
        "description": "@throws java.lang.UnsupportedOperationException always.",
        "guard": {
          "condition": "true",
          "description": "always."
        }
      }
    ],
    "post": [],
    "pre": []
  }
]