[
  {
    "operation": {
      "classname": "com.google.common.collect.ContiguousSet",
      "name": "range",
      "parameterTypes": []
    },
    "identifiers": {
      "parameters": [],
      "receiverName": "receiverObjectID",
      "returnName": "methodResultID"
    },
    "throws": [
      {
        "exception": "java.util.NoSuchElementException",
        "description": "@throws java.util.NoSuchElementException this set is empty.",
        "guard": {
          "condition": "receiverObjectID.isEmpty()",
          "description": "this set is empty."
        }
      }
    ],
    "post": [],
    "pre": []
  },
  {
    "operation": {
      "classname": "com.google.common.collect.ContiguousSet",
      "name": "range",
      "parameterTypes": [
        "com.google.common.collect.BoundType",
        "com.google.common.collect.BoundType"
      ]
    },
    "identifiers": {
      "parameters": [
        "lowerBoundType",
        "upperBoundType"
      ],
      "receiverName": "receiverObjectID",
      "returnName": "methodResultID"
    },
    "throws": [
      {
        "exception": "java.util.NoSuchElementException",
        "description": "@throws java.util.NoSuchElementException this set is empty.",
        "guard": {
          "condition": "receiverObjectID.isEmpty()",
          "description": "this set is empty."
        }
      }
    ],
    "post": [],
    "pre": []
  },
  {
    "operation": {
      "classname": "com.google.common.collect.ContiguousSet",
      "name": "builder",
      "parameterTypes": []
    },
    "identifiers": {
      "parameters": [],
      "receiverName": "receiverObjectID",
      "returnName": "methodResultID"
    },
    "throws": [
      {
        "exception": "java.lang.UnsupportedOperationException",
        "description": "@throws java.lang.UnsupportedOperationException always.",
        "guard": {
          "condition": "true",
          "description": "always."
        }
      }
    ],
    "post": [],
    "pre": []
  }
]