[
  {
    "operation": {
      "classname": "org.apache.commons.math3.optimization.direct.NelderMeadSimplex",
      "name": "org.apache.commons.math3.optimization.direct.NelderMeadSimplex",
      "parameterTypes": [
        "[D",
        "double",
        "double",
        "double",
        "double"
      ]
    },
    "identifiers": {
      "parameters": [
        "steps",
        "rho",
        "khi",
        "gamma",
        "sigma"
      ],
      "receiverName": "receiverObjectID",
      "returnName": "methodResultID"
    },
    "throws": [
      {
        "exception": "java.lang.IllegalArgumentException",
        "description": "@throws java.lang.IllegalArgumentException one of the steps is zero.",
        "guard": {
          "condition": "steps.length==0",
          "description": "one of the steps is zero."
        }
      }
    ],
    "post": [],
    "pre": []
  }
]