[
  {
    "operation": {
      "classname": "org.apache.commons.math3.geometry.spherical.oned.ArcsSet",
      "name": "org.apache.commons.math3.geometry.spherical.oned.ArcsSet",
      "parameterTypes": [
        "double",
        "double",
        "double"
      ]
    },
    "identifiers": {
      "parameters": [
        "lower",
        "upper",
        "tolerance"
      ],
      "receiverName": "receiverObjectID",
      "returnName": "methodResultID"
    },
    "throws": [
      {
        "exception": "org.apache.commons.math3.exception.NumberIsTooLargeException",
        "description": "@throws org.apache.commons.math3.exception.NumberIsTooLargeException lower is greater than upper.",
        "guard": {
          "condition": "lower>upper",
          "description": "lower is greater than upper."
        }
      }
    ],
    "post": [],
    "pre": []
  }
]