[
  {
    "operation": {
      "classname": "org.apache.commons.math3.util.MultidimensionalCounter",
      "name": "getCounts",
      "parameterTypes": [
        "int"
      ]
    },
    "identifiers": {
      "parameters": [
        "index"
      ],
      "receiverName": "receiverObjectID",
      "returnName": "methodResultID"
    },
    "throws": [
      {
        "exception": "org.apache.commons.math3.exception.OutOfRangeException",
        "description": "@throws org.apache.commons.math3.exception.OutOfRangeException index is not between 0 and the value returned by getSize() (excluded).",
        "guard": {
          "condition": "(index==0) == false",
          "description": "index is not between 0 and the value returned by getSize() (excluded)."
        }
      }
    ],
    "post": [],
    "pre": []
  }
]